funcutils/__init__.py
funcutils/py.typed
python_funcutils-0.0.1.dist-info/METADATA
python_funcutils-0.0.1.dist-info/WHEEL
python_funcutils-0.0.1.dist-info/licenses/LICENSE
python_funcutils-0.0.1.dist-info/RECORD
